imginit/__init__.py
imginit-1.0a1.dist-info/LICENSE
imginit-1.0a1.dist-info/METADATA
imginit-1.0a1.dist-info/WHEEL
imginit-1.0a1.dist-info/top_level.txt
imginit-1.0a1.dist-info/RECORD
