Metadata-Version: 2.1
Name: imginit
Version: 1.0a1
Summary: CLI application for bulk image instantiation with basic feature support
Home-page: https://github.com/issuemeaname/imginit
Author: issuemeaname
Author-email: issuemeaname@gmail.com
License: UNKNOWN
Platform: UNKNOWN
Classifier: Programming Language :: Python :: 3
Classifier: License :: OSI Approved :: MIT License
Classifier: Operating System :: OS Independent
